gaussbio3d/__init__.py
gaussbio3d/config.py
gaussbio3d/session.py
gaussbio3d/core/__init__.py
gaussbio3d/core/geometry.py
gaussbio3d/core/gli.py
gaussbio3d/core/gli_segment.py
gaussbio3d/core/gpu.py
gaussbio3d/core/pairwise_gli.py
gaussbio3d/features/__init__.py
gaussbio3d/features/descriptor.py
gaussbio3d/features/node_features.py
gaussbio3d/features/pairwise.py
gaussbio3d/features/segment_j_features.py
gaussbio3d/features/topo_features.py
gaussbio3d/io/__init__.py
gaussbio3d/io/mol.py
gaussbio3d/io/pdb.py
gaussbio3d/molecules/__init__.py
gaussbio3d/molecules/ligand.py
gaussbio3d/molecules/nucleic_acid.py
gaussbio3d/molecules/protein.py
gaussbio3d/tasks/__init__.py
gaussbio3d/tasks/dti.py
gaussbio3d/tasks/mti.py
gaussbio3d/tasks/ppi.py
gaussbio3d/topology/ph.py
gaussbio3d/topology/pl.py
gaussbio3d/topology/pthl.py
gaussbio3d/utils/cache.py
gaussbio3d/utils/logging.py
gaussbio3d-0.1.1.dist-info/METADATA
gaussbio3d-0.1.1.dist-info/WHEEL
gaussbio3d-0.1.1.dist-info/top_level.txt
gaussbio3d-0.1.1.dist-info/RECORD
