Metadata-Version: 2.4
Name: gaussbio3d
Version: 0.1.1
Summary: Multiscale Gauss Linking Integral Library for Biomolecular 3D Topology
Home-page: https://github.com/yourusername/GaussBio3D
Author: Your Name
Author-email: Your Name <your.email@example.com>
Requires-Python: >=3.9
Requires-Dist: numpy>=1.20.0
Requires-Dist: biopython>=1.79
Requires-Dist: rdkit-pypi>=2021.9.1
Requires-Dist: tqdm>=4.66
Provides-Extra: jit
Requires-Dist: numba>=0.56; extra == "jit"
Provides-Extra: gpu
Requires-Dist: torch; extra == "gpu"
Provides-Extra: topology
Requires-Dist: ripser>=0.6; extra == "topology"
Provides-Extra: all
Requires-Dist: numba>=0.56; extra == "all"
Requires-Dist: torch; extra == "all"
Requires-Dist: ripser>=0.6; extra == "all"
Dynamic: author
Dynamic: home-page
Dynamic: requires-python
